chastack_utiles_google/__init__.py
chastack_utiles_google/correo.py
chastack_utiles_google/hojas_de_calculo.py
chastack_utiles_google/pruebas.py
chastack_utiles_google/recurso.py
chastack_utiles_google-0.1.6.dist-info/LICENSE
chastack_utiles_google-0.1.6.dist-info/METADATA
chastack_utiles_google-0.1.6.dist-info/WHEEL
chastack_utiles_google-0.1.6.dist-info/top_level.txt
chastack_utiles_google-0.1.6.dist-info/RECORD
