Metadata-Version: 2.2
Name: chastack-utiles-google
Version: 0.1.6
Home-page: https://github.com/Hernanatn/utiles_google
Author: Hernán A. Teszkiewicz Novick
Author-email: "Hernán A.T.N." <herni@cajadeideas.ar>
Requires-Python: >=3.12
License-File: LICENSE
Requires-Dist: requests
Requires-Dist: google-api-python-client
Requires-Dist: google-auth-httplib2
Requires-Dist: google-auth-oauthlib
Requires-Dist: sobrecargar
Requires-Dist: solteron
Dynamic: author
Dynamic: home-page
